skywinder/__init__.py
skywinder/communication/__init__.py
skywinder/communication/camera_communicator.py
skywinder/communication/command_classes.py
skywinder/communication/command_table.py
skywinder/communication/constants.py
skywinder/communication/downlink_classes.py
skywinder/communication/file_format_classes.py
skywinder/communication/housekeeping_classes.py
skywinder/communication/human_readable_housekeeping_mapping.py
skywinder/communication/lidar.py
skywinder/communication/packet_classes.py
skywinder/communication/pyro_simple_server.py
skywinder/communication/short_status.py
skywinder/communication/sip_data_logger.py
skywinder/communication/streamlined_communicator.py
skywinder/communication/uplink_classes.py
skywinder/communication/tests/SIP_communication_simulator.py
skywinder/communication/tests/__init__.py
skywinder/communication/tests/camera_communicator_tests.py
skywinder/communication/tests/generate_bad_packets.py
skywinder/communication/tests/housekeeping_classes_tests.py
skywinder/communication/tests/test_command_classes.py
skywinder/communication/tests/test_commands.py
skywinder/communication/tests/test_downlinks.py
skywinder/communication/tests/test_file_formats.py
skywinder/communication/tests/test_lidar.py
skywinder/communication/tests/test_packet_classes.py
skywinder/communication/tests/test_packet_interpretation.py
skywinder/communication/tests/test_short_status.py
skywinder/communication/tests/test_sip_uplink_decoding.py
skywinder/ground/__init__.py
skywinder/ground/command_history.py
skywinder/ground/commanding.py
skywinder/ground/ground_configuration.py
skywinder/ground/ground_index.py
skywinder/ground/gse_received_image_viewer.py
skywinder/ground/gse_receiver.py
skywinder/ground/gse_receiver_manager.py
skywinder/ground/jpeg_filler.py
skywinder/ground/lidar_command_relay.py
skywinder/ground/lidar_file_relay.py
skywinder/ground/lowrate_monitor.py
skywinder/ground/short_status_format.py
skywinder/ground/streamlined_commanding.py
SkyWinder-0.0.3.dist-info/LICENSE.md
SkyWinder-0.0.3.dist-info/METADATA
SkyWinder-0.0.3.dist-info/WHEEL
SkyWinder-0.0.3.dist-info/top_level.txt
SkyWinder-0.0.3.dist-info/RECORD
