Metadata-Version: 2.1
Name: SkyWinder
Version: 0.0.3
Summary: A package for instrument control, telemetry, and image analysis for aeronomy experiments
Home-page: https://github.com/PolarMesosphericClouds/SkyWinder
Author: Carl Bjorn Kjellstrand
Author-email: bkjell@gmail.com
Classifier: Programming Language :: Python :: 3
Classifier: License :: OSI Approved :: BSD License
Classifier: Operating System :: OS Independent
Requires-Python: >=3.6
License-File: LICENSE.md
